Workbook

Sheet Read me
A1: CINDERELLA CORP. — BC FULL-STACK MODEL
A2: How to use
A3: • Change any yellow input cell on the Assumptions tab; every other tab recalculates.
A4: • Two scenarios run side by side: BASE (conservative) and REACH (national-hit ceiling).
A5: • All figures are $millions, single-season, one SPV (Boston College).
A7: Structure
A8: • Layer 1 (team commercial): SPV takes 80% of revenue ABOVE the school's ~$4M baseline; school keeps baseline + 20%.
A9: • Layer 2 (show & media): 100% SPV. Production is financed separately by EverWonder (recoup +10% off the license),
A10: so this layer is high-margin — production is NOT an SPV cost.
A11: • Layer 3 (conference): a services fee indexed to BC's ACC merit distribution — NOT a media-rights assignment (compliance).
A12: • Parent (Cinderella Corp) takes 40% of SPV profit + a 2% management fee + a one-time franchise fee.
A14: NIL structure (important)
... A32: NOT financial advice — a planning model with estimated inputs. Verify all figures before external use.

Sheet Assumptions
A1: CINDERELLA CORP. — BOSTON COLLEGE FULL-STACK MODEL
A2: Assumptions & Drivers · all figures in $millions unless noted · single-season SPV · 2026-07-23
A4: DRIVER | B4: NOTES | C4: BASE | D4: REACH
A5: REV-SHARE PARAMETERS
A6: Bucket 1 baseline (school keeps 100%) | B6: current commercial, ex-conference | C6: 4 | D6: 4
A7: SPV share above baseline | B7: 80/20 split | C7: 0.8 | D7: 0.8
A8: LAYER 1 — TEAM COMMERCIAL (with MC)
A9: Gate — Conte Forum (8,606) | B9: revived, premium pricing | C9: 5 | D9: 6
A10: TD Garden marquee games (19,600) | B10: 2–3 games/yr | C10: 2 | D10: 4
A11: MMR + sponsorship | B11: Van Wagner + MC-originated | C11: 6 | D11: 9
A12: Jersey / practice patch | B12: new inventory | C12: 1.5 | D12: 3
A13: Premium / suites / hospitality | C13: 2 | D13: 3
A14: Conte naming rights | B14: big-market property | C14: 1.5 | D14: 3
A15: LAYER 2 — SHOW & MEDIA (100% SPV)
A16: Streaming license (6 hrs) | B16: $1M/hr base, $2M/hr reach | C16: 6 | D16: 12
A17: Presenting / title sponsor | B17: 'presented by' | C17: 4 | D17: 8
A18: Official partners (3–5 tiers) | C18: 3 | D18: 6
A19: Product placement / integration | C19: 1 | D19: 2
A20: Live-game streaming | B20: DTC / international | C20: 1 | D20: 3
A21: Content network (podcast/social/BTS) | C21: 1.5 | D21: 4
A22: Merch / D2C | C22: 1.5 | D22: 4
A23: (less) Production recoup | B23: EverWonder cost +10%, off license | C23: 4 | D23: 7
A24: LAYER 3 — CONFERENCE
A25: Conference success fee (services) | B25: ACC-merit indexed, from gen. funds | C25: 1.5 | D25: 3
A26: SPV COSTS
A27: Roster / NIL (third-party, via SPV) | B27: uncapped; ON TOP of school's ~$3M cap; NIL Go FMV-vetted | C27: 12 | D27: 13
A28: SPV operating costs | B28: ops / staff / on-site | C28: 1.5 | D28: 2
A29: PARENT / STRUCTURE
A30: Parent equity in SPV | C30: 0.4 | D30: 0.4
A31: Management fee (% of SPV revenue) | C31: 0.02 | D31: 0.02
A32: Franchise fee (one-time) | C32: 1.5 | D32: 1.5
A33: SEED WATERFALL (parent-level)
A34: Seed raised | B34: Ankur / Tabor | C34: 1.5 | D34: 1.5
A35: Tier 1 rate — to 1x | B35: of gross | C35: 0.5 | D35: 0.5
A36: Tier 2 rate — 1x to 2x | B36: of gross | C36: 0.1 | D36: 0.1
A37: Tier 3 rate — after 2x | B37: of gross | C37: 0.15 | D37: 0.15

Sheet SPV Full-Stack P&L
A1: SPV FULL-STACK P&L — BOSTON COLLEGE (single season)
A2: live — driven by the Assumptions tab · $millions
A4: LINE | B4: BASE | C4: REACH | D4: NOTE
A5: LAYER 1 — TEAM COMMERCIAL (Bucket 1, rev-shared)
A6: Bucket 1 total (with MC) | B6: =Assumptions!C9+Assumptions!C10+Assumptions!C11+Assumptions!C12+Assumptions!C13+Assumptions!C14 | C6: =Assumptions!D9+Assumptions!D10+Assumptions!D11+Assumptions!D12+Assumptions!D13+Assumptions!D14 | D6: sum of team properties
A7: less: baseline (school keeps 100%) | B7: =-Assumptions!C6 | C7: =-Assumptions!D6 | D7: current commercial
A8: =Incremental revenue above baseline | B8: =B6+B7 | C8: =C6+C7 | D8: what the split applies to
A9: SPV take — Layer 1 (80% of increment) | B9: =B8*Assumptions!C7 | C9: =C8*Assumptions!D7 | D9: school keeps baseline + 20%
A10: LAYER 2 — SHOW & MEDIA (Bucket 2, 100% SPV)
A11: Bucket 2 gross | B11: =Assumptions!C16+Assumptions!C17+Assumptions!C18+Assumptions!C19+Assumptions!C20+Assumptions!C21+Assumptions!C22 | C11: =Assumptions!D16+Assumptions!D17+Assumptions!D18+Assumptions!D19+Assumptions!D20+Assumptions!D21+Assumptions!D22 | D11: all show/media lines
A12: less: production recoup | B12: =-Assumptions!C23 | C12: =-Assumptions!D23 | D12: EverWonder financed separately
A13: SPV take — Layer 2 (net, 100%) | B13: =B11+B12 | C13: =C11+C12 | D13: high-margin: production not an SPV cost
A14: LAYER 3 — CONFERENCE
A15: SPV take — Layer 3 (success fee) | B15: =Assumptions!C25 | C15: =Assumptions!D25 | D15: services fee, not media-rights
A16: SPV REVENUE
A17: TOTAL SPV REVENUE | B17: =B9+B13+B15 | C17: =C9+C13+C15 | D17: all three layers
A18: SPV COSTS
A19: Roster / NIL | B19: =-Assumptions!C27 | C19: =-Assumptions!D27 | D19: 3rd-party NIL, uncapped; on top of school cap
A20: SPV operating costs | B20: =-Assumptions!C28 | C20: =-Assumptions!D28
A21: Management fee (to parent) | B21: =-Assumptions!C31*B17 | C21: =-Assumptions!D31*C17 | D21: 2% of SPV revenue
A22: Total SPV costs | B22: =B19+B20+B21 | C22: =C19+C20+C21
A23: SPV PROFIT & DISTRIBUTION
A24: SPV PROFIT (pre-equity split) | B24: =B17+B22 | C24: =C17+C22 | D24: revenue less all costs
A25: Parent equity share (40% of profit) | B25: =B24*Assumptions!C30 | C25: =C24*Assumptions!D30
A26: Other SPV investors (60% of profit) | B26: =B24*(1-Assumptions!C30) | C26: =C24*(1-Assumptions!D30)
A27: PARENT TOTAL TAKE (40% + mgmt fee + franchise fee) | B27: =B25+Assumptions!C31*B17+Assumptions!C32 | C27: =C25+Assumptions!D31*C17+Assumptions!D32 | D27: flows to Cinderella Corp
A28: MEMO — SCHOOL (BC) ECONOMICS
A29: BC keeps: baseline + 20% of increment | B29: =Assumptions!C6+B8*(1-Assumptions!C7) | C29: =Assumptions!D6+C8*(1-Assumptions!D7) | D29: up from ~$4M, fronting nothing
A30: BC uplift vs current baseline (x) | B30: =B29/Assumptions!C6 | C30: =C29/Assumptions!D6 | D30: multiple of today
A31: BENCHMARK
A32: Duke men's basketball revenue (2023-24) | B32: 44.8 | C32: 44.8 | D32: EADA #1 in nation
A33: Cinderella-BC enterprise total (team+show) | B33: =B6+B11+B12+B15 | C33: =C6+C11+C12+C15 | D33: all revenue the venture touches
A34: % of Duke (enterprise basis) | B34: =B33/B32 | C34: =C33/C32 | D34: team-medium + media-heavy = Duke total

Sheet Seed Waterfall
A1: SEED WATERFALL — parent distribution (single-SPV illustration)
A2: 50% of gross to 1x, then 10% to 2x, then 15% · applied to Parent Total Take · $M
A3: Note: real waterfall is CUMULATIVE across all SPVs & years — see capital-deployment workbook. This shows one BC season as if first money in.
A5: LINE | B5: BASE | C5: REACH | D5: NOTE
A6: Parent Total Take (gross into waterfall) | B6: ='SPV Full-Stack P&L'!B27 | C6: ='SPV Full-Stack P&L'!C27 | D6: from P&L
A7: Gross needed to return 1x | B7: =(Assumptions!C34/Assumptions!C35) | C7: =(Assumptions!D34/Assumptions!D35) | D7: at 50% rate
A8: Cumulative gross to reach 2x | B8: =(Assumptions!C34/Assumptions!C35+Assumptions!C34/Assumptions!C36) | C8: =(Assumptions!D34/Assumptions!D35+Assumptions!D34/Assumptions!D36) | D8: add 10% band
A9: Seed investors receive (this period) | B9: =Assumptions!C35*MIN(B6,(Assumptions!C34/Assumptions!C35))+Assumptions!C36*MIN(MAX(B6-(Assumptions!C34/Assumptions!C35),0),Assumptions!C34/Assumptions!C36)+Assumptions!C37*MAX(B6-(Assumptions!C34/Assumptions!C35+Assumptions!C34/Assumptions!C36),0) | C9: =Assumptions!D35*MIN(C6,(Assumptions!D34/Assumptions!D35))+Assumptions!D36*MIN(MAX(C6-(Assumptions!D34/Assumptions!D35),0),Assumptions!D34/Assumptions!D36)+Assumptions!D37*MAX(C6-(Assumptions!D34/Assumptions!D35+Assumptions!D34/Assumptions!D36),0) | D9: 50/10/15 of gross
A10: Seed cumulative MOIC (this period) | B10: =B9/Assumptions!C34 | C10: =C9/Assumptions!D34 | D10: x of $1.5M
A11: Parent retains (after seed) | B11: =B6-B9 | C11: =C6-C9 | D11: to Cinderella Corp / founder
