Workbook

Sheet Assumptions
A1: Making Cinderella — Talent Comp vs Investor MOIC
A2: Illustrative model. Yellow cells are inputs — edit them and every tier updates.
A4: INPUTS (edit)
A5: Investor capital into the SPV ($) | B5: 12000000
A6: Parent base equity — pre-talent (%) | B6: 0.4
A7: Investor base equity — pre-talent (%) | B7: =1-B5
A9: Distributable to equity over SPV life — BEAR ($) | B9: 28000000
A10: Distributable to equity over SPV life — BASE ($) | B10: 50000000
A11: Distributable to equity over SPV life — BULL ($) | B11: 80000000
A14: HOW IT WORKS
A15: • 'Distributable to equity' = total cash available to the SPV cap table over its life,
A16: BEFORE the talent cash fee (which is modeled as an SPV cost, paid first).
A17: • Investor MOIC = investor's share of (distributable − talent cash) ÷ investor capital in.
A18: • Two ways talent equity can dilute:
A19: – PRO-RATA: talent % comes off the whole cap table → hits investors directly (default columns).
A20: – PARENT-ABSORBED: talent % comes out of the PARENT's promote → investors untouched (last column).
A21: • KEY LEVER: negotiate talent equity to come (at least partly) from the parent's 40%, not pro-rata.
A22: Same offer to the talent; very different investor return. See how the last column barely moves.
A23: • Baseline row (no talent) shows the ceiling you're diluting from.
A24: • All figures illustrative — replace the four yellow inputs with the real SPV numbers.

Sheet Talent Grid
A1: Talent Comp Tiers → Investor MOIC
A2: Cash floor + equity grant per 12-month season. Investor MOIC under three revenue scenarios.
A4: Tier | B4: Example | C4: Cash floor ($) | D4: Equity % | E4: Talent take — Base ($) | F4: Inv MOIC — Bear | G4: Inv MOIC — Base | H4: Inv MOIC — Bull | I4: Inv MOIC — Base (parent-absorbed) | J4: Parent equity left (absorbed)
A5: No talent (baseline) | B5: — | C5: 0 | D5: 0 | E5: =C5+D5*(Assumptions!$B$10-C5) | F5: =Assumptions!$B$7*(1-D5)*(Assumptions!$B$9-C5)/Assumptions!$B$5 | G5: =Assumptions!$B$7*(1-D5)*(Assumptions!$B$10-C5)/Assumptions!$B$5 | H5: =Assumptions!$B$7*(1-D5)*(Assumptions!$B$11-C5)/Assumptions!$B$5 | I5: =Assumptions!$B$7*(Assumptions!$B$10-C5)/Assumptions!$B$5 | J5: =Assumptions!$B$6-D5
A6: Co-lead ex-athlete | B6: Tim Hardaway | C6: 100000 | D6: 0.1 | E6: =C6+D6*(Assumptions!$B$10-C6) | F6: =Assumptions!$B$7*(1-D6)*(Assumptions!$B$9-C6)/Assumptions!$B$5 | G6: =Assumptions!$B$7*(1-D6)*(Assumptions!$B$10-C6)/Assumptions!$B$5 | H6: =Assumptions!$B$7*(1-D6)*(Assumptions!$B$11-C6)/Assumptions!$B$5 | I6: =Assumptions!$B$7*(Assumptions!$B$10-C6)/Assumptions!$B$5 | J6: =Assumptions!$B$6-D6
A7: Iconic legend | B7: Julius Erving | C7: 275000 | D7: 0.125 | E7: =C7+D7*(Assumptions!$B$10-C7) | F7: =Assumptions!$B$7*(1-D7)*(Assumptions!$B$9-C7)/Assumptions!$B$5 | G7: =Assumptions!$B$7*(1-D7)*(Assumptions!$B$10-C7)/Assumptions!$B$5 | H7: =Assumptions!$B$7*(1-D7)*(Assumptions!$B$11-C7)/Assumptions!$B$5 | I7: =Assumptions!$B$7*(Assumptions!$B$10-C7)/Assumptions!$B$5 | J7: =Assumptions!$B$6-D7
A8: National star | B8: big comedian/musician | C8: 700000 | D8: 0.2 | E8: =C8+D8*(Assumptions!$B$10-C8) | F8: =Assumptions!$B$7*(1-D8)*(Assumptions!$B$9-C8)/Assumptions!$B$5 | G8: =Assumptions!$B$7*(1-D8)*(Assumptions!$B$10-C8)/Assumptions!$B$5 | H8: =Assumptions!$B$7*(1-D8)*(Assumptions!$B$11-C8)/Assumptions!$B$5 | I8: =Assumptions!$B$7*(Assumptions!$B$10-C8)/Assumptions!$B$5 | J8: =Assumptions!$B$6-D8
A9: A-list standalone | B9: Adam Sandler / Denzel | C9: 1000000 | D9: 0.3 | E9: =C9+D9*(Assumptions!$B$10-C9) | F9: =Assumptions!$B$7*(1-D9)*(Assumptions!$B$9-C9)/Assumptions!$B$5 | G9: =Assumptions!$B$7*(1-D9)*(Assumptions!$B$10-C9)/Assumptions!$B$5 | H9: =Assumptions!$B$7*(1-D9)*(Assumptions!$B$11-C9)/Assumptions!$B$5 | I9: =Assumptions!$B$7*(Assumptions!$B$10-C9)/Assumptions!$B$5 | J9: =Assumptions!$B$6-D9
A11: Reads: pro-rata dilution (Bear/Base/Bull) is what investors feel if talent equity comes off the whole table.
A12: The 'parent-absorbed' column ≈ the no-talent MOIC — proof that WHERE the equity comes from matters more than how much.
A13: If 'Parent equity left' goes negative, the parent can't fully absorb that grant (e.g., two A-listers) — then some hits investors.
