Workbook

Sheet Three-School Projection
A1: Making Cinderella — Season 1 MBB Revenue: Current / Base / Reach (figures in $000s; estimates)
B2: ST. JOSEPH'S (Hagan 4,200 · A-10) | E2: DAVIDSON (Belk 5,223 · Curry alma mater) | H2: HAWAII (Stan Sheriff 10,300 · Big West)
A3: Revenue line item | B3: Current | C3: Base | D3: Reach | E3: Current | F3: Base | G3: Reach | H3: Current | I3: Base | J3: Reach
A4: Ticketing & game-day
A5: Season ticket sales | B5: 210 | C5: 1200 | D5: 1800 | E5: 270 | F5: 1470 | G5: 2200 | H5: 450 | I5: 2030 | J5: 3000
A6: Single-game & group ticket sales | B6: 120 | C6: 2220 | D6: 3500 | E6: 150 | F6: 2230 | G6: 3500 | H6: 210 | I6: 1630 | J6: 2500
A7: Premium seating (suites, club, courtside) | B7: 40 | C7: 510 | D7: 800 | E7: 80 | F7: 650 | G7: 1000 | H7: 90 | I7: 590 | J7: 900
A8: Postseason ticket (allotment margin — conf/NCAA keep the gate) | B8: 10 | C8: 40 | D8: 60 | E8: 20 | F8: 60 | G8: 80 | H8: 10 | I8: 30 | J8: 50
A9: Concessions (program's share) | B9: 40 | C9: 330 | D9: 500 | E9: 40 | F9: 360 | G9: 550 | H9: 90 | I9: 470 | J9: 700
A10: Parking | B10: 20 | C10: 190 | D10: 300 | E10: 20 | F10: 220 | G10: 350 | H10: 40 | I10: 230 | J10: 350
A11: Game-day novelty / program / merch | B11: 20 | C11: 320 | D11: 500 | E11: 40 | F11: 390 | G11: 600 | H11: 40 | I11: 330 | J11: 500
A12: Subtotal — Ticketing & game-day | B12: =SUM(B5:B11) | C12: =SUM(C5:C11) | D12: =SUM(D5:D11) | E12: =SUM(E5:E11) | F12: =SUM(F5:F11) | G12: =SUM(G5:G11) | H12: =SUM(H5:H11) | I12: =SUM(I5:I11) | J12: =SUM(J5:J11)
A14: Media & broadcasting
A15: Conference media-rights distribution | B15: 450 | C15: 450 | D15: 450 | E15: 450 | F15: 450 | G15: 450 | H15: 250 | I15: 250 | J15: 250
A16: Third-tier / local media (school-retained) | B16: 20 | C16: 160 | D16: 250 | E16: 20 | F16: 190 | G16: 300 | H16: 20 | I16: 130 | J16: 200
A17: School-controlled streaming | B17: 10 | C17: 240 | D17: 400 | E17: 10 | F17: 270 | G17: 450 | H17: 10 | I17: 210 | J17: 350
A18: Radio broadcast rights | B18: 10 | C18: 80 | D18: 120 | E18: 20 | F18: 100 | G18: 150 | H18: 20 | I18: 70 | J18: 100
A19: Subtotal — Media & broadcasting | B19: =SUM(B15:B18) | C19: =SUM(C15:C18) | D19: =SUM(D15:D18) | E19: =SUM(E15:E18) | F19: =SUM(F15:F18) | G19: =SUM(G15:G18) | H19: =SUM(H15:H18) | I19: =SUM(I15:I18) | J19: =SUM(J15:J18)
A21: Conference & NCAA distributions
A22: Conference revenue distribution (non-media share) | B22: 350 | C22: 350 | D22: 350 | E22: 350 | F22: 350 | G22: 350 | H22: 200 | I22: 200 | J22: 200
A23: Conference tournament revenue share | B23: 80 | C23: 80 | D23: 80 | E23: 80 | F23: 80 | G23: 80 | H23: 50 | I23: 50 | J23: 50
A24: NCAA Tournament units / Perf. Fund | B24: 40 | C24: 570 | D24: 700 | E24: 60 | F24: 650 | G24: 800 | H24: 30 | I24: 490 | J24: 600
A25: NCAA broad-based distributions | B25: 210 | C25: 210 | D25: 210 | E25: 210 | F25: 210 | G25: 210 | H25: 190 | I25: 190 | J25: 190
A26: Subtotal — Conference & NCAA distributions | B26: =SUM(B22:B25) | C26: =SUM(C22:C25) | D26: =SUM(D22:D25) | E26: =SUM(E22:E25) | F26: =SUM(F22:F25) | G26: =SUM(G22:G25) | H26: =SUM(H22:H25) | I26: =SUM(I22:I25) | J26: =SUM(J22:J25)
A28: Corporate sponsorship & multimedia rights
A29: Multimedia rights guarantee (Learfield etc.) | B29: 90 | C29: 520 | D29: 800 | E29: 100 | F29: 580 | G29: 900 | H29: 120 | I29: 530 | J29: 800
A30: Corporate / category sponsorships (school) | B30: 80 | C30: 450 | D30: 700 | E30: 90 | F30: 550 | G30: 850 | H30: 100 | I30: 460 | J30: 700
A31: Arena / court naming rights (MBB share) | B31: 20 | C31: 130 | D31: 200 | E31: 20 | F31: 190 | G31: 300 | H31: 30 | I31: 160 | J31: 250
A32: Signage / LED / in-arena advertising | B32: 30 | C32: 190 | D32: 300 | E32: 40 | F32: 230 | G32: 350 | H32: 40 | I32: 200 | J32: 300
A33: Jersey patch (school; national patch = Bkt2) | B33: 0 | C33: 90 | D33: 150 | E33: 0 | F33: 120 | G33: 200 | H33: 0 | I33: 70 | J33: 120
A34: Coach's show / radio show sponsorship | B34: 10 | C34: 90 | D34: 150 | E34: 20 | F34: 120 | G34: 180 | H34: 10 | I34: 80 | J34: 120
A35: Digital & social sponsorship (national = Bkt2) | B35: 10 | C35: 90 | D35: 150 | E35: 10 | F35: 120 | G35: 200 | H35: 10 | I35: 80 | J35: 120
A36: Subtotal — Corporate sponsorship & multimedia rights | B36: =SUM(B29:B35) | C36: =SUM(C29:C35) | D36: =SUM(D29:D35) | E36: =SUM(E29:E35) | F36: =SUM(F29:F35) | G36: =SUM(G29:G35) | H36: =SUM(H29:H35) | I36: =SUM(I29:I35) | J36: =SUM(J29:J35)
A38: Philanthropy & donor
A39: Annual fund / booster donations | B39: 180 | C39: 740 | D39: 1200 | E39: 270 | F39: 1110 | G39: 1800 | H39: 150 | I39: 620 | J39: 1000
A40: Seat-related required donations (PSLs) | B40: 90 | C40: 480 | D40: 800 | E40: 150 | F40: 730 | G40: 1200 | H40: 60 | I40: 410 | J40: 700
A41: Major gifts & endowment (MBB-specific) | B41: 60 | C41: 580 | D41: 1000 | E41: 120 | F41: 880 | G41: 1500 | H41: 40 | I41: 510 | J41: 900
A42: Capital-campaign gifts (facilities) | B42: 30 | C42: 230 | D42: 400 | E42: 60 | F42: 410 | G42: 700 | H42: 30 | I42: 290 | J42: 500
A43: Collective / NIL donor contributions | B43: 90 | C43: 700 | D43: 1200 | E43: 150 | F43: 890 | G43: 1500 | H43: 80 | I43: 590 | J43: 1000
A44: Subtotal — Philanthropy & donor | B44: =SUM(B39:B43) | C44: =SUM(C39:C43) | D44: =SUM(D39:D43) | E44: =SUM(E39:E43) | F44: =SUM(F39:F43) | G44: =SUM(G39:G43) | H44: =SUM(H39:H43) | I44: =SUM(I39:I43) | J44: =SUM(J39:J43)
A46: Apparel & licensing
A47: Shoe/apparel contract (cash + product) | B47: 200 | C47: 200 | D47: 200 | E47: 300 | F47: 300 | G47: 300 | H47: 150 | I47: 150 | J47: 150
A48: Trademark / logo licensing royalties | B48: 10 | C48: 240 | D48: 400 | E48: 20 | F48: 370 | G48: 600 | H48: 10 | I48: 180 | J48: 300
A49: Team retail merchandise sales | B49: 30 | C49: 490 | D49: 800 | E49: 40 | F49: 620 | G49: 1000 | H49: 40 | I49: 380 | J49: 600
A50: Video-game / EA royalties | B50: 10 | C50: 60 | D50: 100 | E50: 10 | F50: 90 | G50: 150 | H50: 10 | I50: 50 | J50: 80
A51: Subtotal — Apparel & licensing | B51: =SUM(B47:B50) | C51: =SUM(C47:C50) | D51: =SUM(D47:D50) | E51: =SUM(E47:E50) | F51: =SUM(F47:F50) | G51: =SUM(G47:G50) | H51: =SUM(H47:H50) | I51: =SUM(I47:I50) | J51: =SUM(J47:J50)
A53: Guarantees & scheduling
A54: Guarantee ('buy') game income | B54: 90 | C54: 410 | D54: 600 | E54: 90 | F54: 410 | G54: 600 | H54: 120 | I54: 360 | J54: 500
A55: Neutral-site / MTE appearance fees | B55: 30 | C55: 510 | D55: 800 | E55: 40 | F55: 570 | G55: 900 | H55: 90 | I55: 470 | J55: 700
A56: Early-season / holiday tournament payouts | B56: 20 | C56: 260 | D56: 400 | E56: 30 | F56: 320 | G56: 500 | H56: 40 | I56: 260 | J56: 400
A57: Exhibition / charity game revenue | B57: 10 | C57: 70 | D57: 100 | E57: 10 | F57: 80 | G57: 120 | H57: 10 | I57: 50 | J57: 80
A58: Subtotal — Guarantees & scheduling | B58: =SUM(B54:B57) | C58: =SUM(C54:C57) | D58: =SUM(D54:D57) | E58: =SUM(E54:E57) | F58: =SUM(F54:F57) | G58: =SUM(G54:G57) | H58: =SUM(H54:H57) | I58: =SUM(I54:I57) | J58: =SUM(J54:J57)
A60: Camps, clinics & operations
A61: Basketball camps & clinics revenue | B61: 40 | C61: 270 | D61: 400 | E61: 60 | F61: 350 | G61: 500 | H61: 40 | I61: 240 | J61: 350
A62: Coach's camps | B62: 20 | C62: 140 | D62: 200 | E62: 30 | F62: 170 | G62: 250 | H62: 20 | I62: 100 | J62: 150
A63: Facility rentals (MBB-allocated) | B63: 20 | C63: 100 | D63: 150 | E63: 20 | F63: 120 | G63: 180 | H63: 30 | I63: 170 | J63: 250
A64: Subtotal — Camps, clinics & operations | B64: =SUM(B61:B63) | C64: =SUM(C61:C63) | D64: =SUM(D61:D63) | E64: =SUM(E61:E63) | F64: =SUM(F61:F63) | G64: =SUM(G61:G63) | H64: =SUM(H61:H63) | I64: =SUM(I61:I63) | J64: =SUM(J61:J63)
A66: Institutional & other support
A67: Direct institutional / university support | B67: 240 | C67: 320 | D67: 400 | E67: 180 | F67: 240 | G67: 300 | H67: 360 | I67: 530 | J67: 700
A68: Student-fee allocation | B68: 60 | C68: 80 | D68: 100 | E68: 30 | F68: 40 | G68: 50 | H68: 180 | I68: 290 | J68: 400
A69: Direct state / government support | B69: 0 | C69: 0 | D69: 0 | E69: 0 | F69: 0 | G69: 0 | H69: 240 | I69: 420 | J69: 600
A70: Athletics endowment / investment income | B70: 30 | C70: 90 | D70: 150 | E70: 90 | F70: 240 | G70: 400 | H70: 20 | I70: 50 | J70: 80
A71: Third-party in-kind & third-party-paid comp | B71: 20 | C71: 60 | D71: 100 | E71: 20 | F71: 80 | G71: 150 | H71: 20 | I71: 70 | J71: 120
A72: Other / misc operating revenue | B72: 20 | C72: 60 | D72: 100 | E72: 20 | F72: 70 | G72: 120 | H72: 20 | I72: 60 | J72: 100
A73: Subtotal — Institutional & other support | B73: =SUM(B67:B72) | C73: =SUM(C67:C72) | D73: =SUM(D67:D72) | E73: =SUM(E67:E72) | F73: =SUM(F67:F72) | G73: =SUM(G67:G72) | H73: =SUM(H67:H72) | I73: =SUM(I67:I72) | J73: =SUM(J67:J72)
A75: NIL / rev-share era (memo — NOT program revenue; see per-line notes)
A76: Third-party athlete NIL income (memo — athletes' own $, not SPV rev/cost) | B76: 30 | C76: 990 | D76: 1500 | E76: 40 | F76: 1310 | G76: 2000 | H76: 20 | I76: 660 | J76: 1000
A77: Athlete marketing / activation (SPV-produced = Bucket 2) | B77: 20 | C77: 530 | D77: 800 | E77: 30 | F77: 660 | G77: 1000 | H77: 10 | I77: 390 | J77: 600
A78: House-settlement rev-share pool (SPV-funded roster COST) | B78: 0 | C78: 1620 | D78: 2500 | E78: 0 | F78: 1620 | G78: 2500 | H78: 0 | I78: 1620 | J78: 2500
A79: Subtotal — NIL / rev-share era | B79: =SUM(B76:B78) | C79: =SUM(C76:C78) | D79: =SUM(D76:D78) | E79: =SUM(E76:E78) | F79: =SUM(F76:F78) | G79: =SUM(G76:G78) | H79: =SUM(H76:H78) | I79: =SUM(I76:I78) | J79: =SUM(J76:J78)
A81: PROGRAM REVENUE (categories 1–9, excl. NIL) = the total baseline | B81: =B12+B19+B26+B36+B44+B51+B58+B64+B73 | C81: =C12+C19+C26+C36+C44+C51+C58+C64+C73 | D81: =D12+D19+D26+D36+D44+D51+D58+D64+D73 | E81: =E12+E19+E26+E36+E44+E51+E58+E64+E73 | F81: =F12+F19+F26+F36+F44+F51+F58+F64+F73 | G81: =G12+G19+G26+G36+G44+G51+G58+G64+G73 | H81: =H12+H19+H26+H36+H44+H51+H58+H64+H73 | I81: =I12+I19+I26+I36+I44+I51+I58+I64+I73 | J81: =J12+J19+J26+J36+J44+J51+J58+J64+J73
A82: NIL / rev-share funding (memo — SPV-funded cost) | B82: =B79 | C82: =C79 | D82: =D79 | E82: =E79 | F82: =F79 | G82: =G79 | H82: =H79 | I82: =I79 | J82: =J79
A84: SPV ECONOMICS (Bucket 1 above baseline, 80/20; baseline = total current revenue, one lump)
B85: Baseline (total curr.) | C85: Bucket 1 Base w/MC | D85: Bucket 1 Reach w/MC | E85: SPV 80% Base | F85: SPV 80% Reach | G85: School keeps Base | H85: School keeps Reach
A86: St. Joseph's | B86: =B81 | C86: =C12+C19+C36+C51+C58+C64 | D86: =D12+D19+D36+D51+D58+D64 | E86: =0.8*(C86-B86) | F86: =0.8*(D86-B86) | G86: =B86+0.2*(C86-B86) | H86: =B86+0.2*(D86-B86)
A87: Davidson | B87: =E81 | C87: =F12+F19+F36+F51+F58+F64 | D87: =G12+G19+G36+G51+G58+G64 | E87: =0.8*(C87-B87) | F87: =0.8*(D87-B87) | G87: =B87+0.2*(C87-B87) | H87: =B87+0.2*(D87-B87)
A88: Hawaii | B88: =H81 | C88: =I12+I19+I36+I51+I58+I64 | D88: =J12+J19+J36+J51+J58+J64 | E88: =0.8*(C88-B88) | F88: =0.8*(D88-B88) | G88: =B88+0.2*(C88-B88) | H88: =B88+0.2*(D88-B88)
A90: NOTES
A91: Reach = full-attachment estimate (celebrity + Netflix + top-10 roster + deep tournament run all landing). Base = Current + a conservative fraction of that uplift (55-65% on commercial lines).
A92: MECHANIC (simplified): baseline = the school's TOTAL current program revenue (one lump, the green PROGRAM REVENUE row). The school keeps the first [baseline] dollars; everything in Bucket 1 above the baseline splits 80/20 (SPV 80, school 20). Not itemized line-by-line.
A93: Bucket 1 = the school's commercial revenue with MC (Ticketing, Media, Sponsorship/MMR, Apparel/Licensing, Guarantees, Camps). SPV 80% = 0.8 x (Bucket 1 w/MC - total baseline). School keeps baseline + 20% of the excess.
A94: Postseason gate: conf tournament & NCAA tournament ticket revenue goes to the CONFERENCE / NCAA, not the school — line reduced to a small allotment margin only.
A95: Concessions & parking DO grow: marquee home games are relocated to big arenas (St. Joe's -> Xfinity Mobile Arena) where the school is the home promoter and keeps/splits the ancillaries.
A96: MMR constraint (Learfield/Playfly own school inventory): Bucket 1 sponsorship kept modest. National / Netflix-grade sponsor + patch = SPV IP (Bucket 2, off this sheet), not school MMR inventory.
A97: Apparel shoe contract held FLAT — multi-year locked deal, no mid-term jump (renewal upside later). Licensing/merch/retail still grow (flexible).
A98: NIL memo lines are NOT program revenue: (1) third-party athlete NIL income = athletes' own earnings (a recruiting benefit, not SPV rev/cost); (2) athlete marketing/activation = SPV-produced Bucket 2; (3) House rev-share pool = SPV-funded roster COST.
A99: Bucket 2 (NOT on this sheet, 100% SPV, ~$15M): Netflix series (10 hrs @ $1.0M rev / $0.6M cost), 3 live games (>$1M rev / $0.3M cost each), national presenting sponsor + patch, athlete-marketing/activation, international + format. Roughly recoups the $15M SPV cost.
A100: Marquee-game relocation assumed: St. Joe's -> Xfinity Mobile Arena (19k); Davidson -> Spectrum Center (19k); Hawaii carried by its 10,300 arena + Diamond Head Classic. All figures ESTIMATES in $000s.

Sheet Bucket 2 (SPV)
A1: Bucket 2 — SPV-only revenue (100% SPV, off the school sheet) ($000s)
A3: Line | B3: Base | C3: Reach
A4: Streaming series (10 hrs @ $1.0M sold / $0.6M cost) | B4: 3200 | C4: 5000 | D4: $400k/hr margin before intl/format
A5: International + format windows | B5: 1500 | C5: 5000 | D5: durable franchise asset; grows w/ library
A6: Live games (3 @ >$1.0M rev / $0.3M cost each) | B6: 2100 | C6: 4000 | D6: school-owned neutral/non-conf games
A7: National presenting sponsor + premium patch | B7: 3000 | C7: 8000 | D7: priced off Netflix eyeballs; SPV IP, not school MMR
A8: MC-originated sponsorship (signage/MMR-scope, ~85% SPV) | B8: 2000 | C8: 6000 | D8: MC sources it, keeps ~85% via originator deal; Learfield ~15%
A9: Content engine / athlete marketing & activation | B9: 500 | C9: 1500 | D9: SPV-produced branded content; players' NIL contracted
A10: Bucket 2 total (SPV) | B10: =SUM(B4:B9) | C10: =SUM(C4:C9)
A12: FULL SPV PICTURE — single season (Bucket 1 share + Bucket 2 − $15M SPV cost)
A13: School | B13: Bkt1 SPV Base | C13: + Bkt2 Base | D13: − SPV cost | E13: =SPV net Base
A14: St. Joseph's | B14: ='Three-School Projection'!E86 | C14: =B10 | D14: -15000 | E14: =B14+C14+D14
A15: Davidson | B15: ='Three-School Projection'!E87 | C15: =B10 | D15: -15000 | E15: =B15+C15+D15
A16: Hawaii | B16: ='Three-School Projection'!E88 | C16: =B10 | D16: -15000 | E16: =B16+C16+D16
A18: School | B18: Bkt1 SPV Reach | C18: + Bkt2 Reach | D18: − SPV cost | E18: =SPV net Reach
A19: St. Joseph's | B19: ='Three-School Projection'!F86 | C19: =C10 | D19: -15000 | E19: =B19+C19+D19
A20: Davidson | B20: ='Three-School Projection'!F87 | C20: =C10 | D20: -15000 | E20: =B20+C20+D20
A21: Hawaii | B21: ='Three-School Projection'!F88 | C21: =C10 | D21: -15000 | E21: =B21+C21+D21
A23: Bucket 2 is 100% SPV and never touches the school sheet or the 80/20 split.
A24: Series & live-game costs are already netted in their lines (EverWonder finances production, recoups cost+10%). The $15M SPV cost = roster/NIL + ops.
A25: MC-originated sponsorship: rather than routing MC-sourced signage/MMR-scope deals through Learfield's fixed guarantee (where the upside gets trapped), MC originates and keeps ~85%. Safer and higher than the 80/20 team-revenue path.
A26: Per-school variance is minor (national platform) — Davidson skews high via the Curry anchor. Reach is the optimistic ceiling; underwrite on Base.
